pyensign/__init__.py
pyensign/ack.py
pyensign/connection.py
pyensign/ensign.py
pyensign/enum.py
pyensign/events.py
pyensign/exceptions.py
pyensign/iterator.py
pyensign/mimetypes.py
pyensign/nack.py
pyensign/projects.py
pyensign/publisher.py
pyensign/status.py
pyensign/stream.py
pyensign/subscriber.py
pyensign/sync.py
pyensign/topics.py
pyensign/version.py
pyensign/api/__init__.py
pyensign/api/v1beta1/__init__.py
pyensign/api/v1beta1/ensign_pb2.py
pyensign/api/v1beta1/ensign_pb2_grpc.py
pyensign/api/v1beta1/event.py
pyensign/api/v1beta1/event_pb2.py
pyensign/api/v1beta1/groups_pb2.py
pyensign/api/v1beta1/query.py
pyensign/api/v1beta1/query_pb2.py
pyensign/api/v1beta1/topic_pb2.py
pyensign/auth/__init__.py
pyensign/auth/client.py
pyensign/auth/interceptor.py
pyensign/auth/tokens.py
pyensign/mimetype/__init__.py
pyensign/mimetype/v1beta1/__init__.py
pyensign/mimetype/v1beta1/mimetype_pb2.py
pyensign/ml/__init__.py
pyensign/ml/dataframe.py
pyensign/region/__init__.py
pyensign/region/v1beta1/__init__.py
pyensign/region/v1beta1/region_pb2.py
pyensign/utils/__init__.py
pyensign/utils/cache.py
pyensign/utils/pbtime.py
pyensign/utils/queue.py
pyensign/utils/rlid.py
pyensign/utils/tasks.py
pyensign/utils/topics.py
pyensign/utils/ulid.py
pyensign-0.12.1b0.dist-info/LICENSE
pyensign-0.12.1b0.dist-info/METADATA
pyensign-0.12.1b0.dist-info/WHEEL
pyensign-0.12.1b0.dist-info/top_level.txt
pyensign-0.12.1b0.dist-info/RECORD
