Metadata-Version: 2.1
Name: pyensign
Version: 0.12.1b0
Summary: Ensign driver, SDK, and helpers for Python
Home-page: https://github.com/rotationalio/pyensign
Download-URL: https://github.com/rotationalio/pyensign/tarball/v0.12.1b0
Author: Patrick Deziel
Author-email: deziel.patrick@gmail.com
Maintainer: Patrick Deziel
Maintainer-email: deziel.patrick@gmail.com
License: BSD
Keywords: python,setup,pypi
Classifier: Development Status :: 4 - Beta
Classifier: Environment :: Console
Classifier: License :: OSI Approved :: BSD License
Classifier: Natural Language :: English
Classifier: Operating System :: OS Independent
Classifier: Programming Language :: Python :: 3
Classifier: Programming Language :: Python :: 3.9
Classifier: Programming Language :: Python :: 3.10
Classifier: Programming Language :: Python :: 3.11
License-File: LICENSE
Requires-Dist: grpcio ==1.59.0
Requires-Dist: protobuf ==4.24.4
Requires-Dist: PyJWT ==2.8.0
Requires-Dist: python-ulid ==2.2.0
Provides-Extra: ml
Requires-Dist: pandas ==2.1.2 ; extra == 'ml'
